SimpleLLMFunc/.DS_Store
SimpleLLMFunc/__init__.py
SimpleLLMFunc/config.py
SimpleLLMFunc/interface/__init__.py
SimpleLLMFunc/interface/key_pool.py
SimpleLLMFunc/interface/llm_interface.py
SimpleLLMFunc/interface/openai_compatible.py
SimpleLLMFunc/interface/token_bucket.py
SimpleLLMFunc/llm_decorator/__init__.py
SimpleLLMFunc/llm_decorator/llm_chat_decorator.py
SimpleLLMFunc/llm_decorator/llm_function_decorator.py
SimpleLLMFunc/llm_decorator/multimodal_types.py
SimpleLLMFunc/llm_decorator/utils.py
SimpleLLMFunc/logger/__init__.py
SimpleLLMFunc/logger/logger.py
SimpleLLMFunc/logger/logger_config.py
SimpleLLMFunc/py.typed
SimpleLLMFunc/tool/__init__.py
SimpleLLMFunc/tool/tool.py
SimpleLLMFunc/type/__init__.py
SimpleLLMFunc/utils.py
simplellmfunc-0.2.13.dist-info/LICENSE
simplellmfunc-0.2.13.dist-info/METADATA
simplellmfunc-0.2.13.dist-info/WHEEL
simplellmfunc-0.2.13.dist-info/RECORD
