Metadata-Version: 2.3
Name: SimpleLLMFunc
Version: 0.2.13
Summary: 一个轻量但完备的LLM/Agent应用开发框架，提供装饰器实现将函数DocString作为Prompt而无需函数体具体实现但能够享受函数定义和类型标注带来效率提升的开发体验。以最Code的方式，用最少的代码将LLM能力集成到任意Python项目中。
Author: Ni Jingzhe
Author-email: nijingzhe@zju.edu.cn
Requires-Python: >=3.10
Classifier: Programming Language :: Python :: 3
Classifier: Programming Language :: Python :: 3.10
Classifier: Programming Language :: Python :: 3.11
Classifier: Programming Language :: Python :: 3.12
Classifier: Programming Language :: Python :: 3.13
Requires-Dist: httpx[socks] (>=0.28.1,<0.29.0)
Requires-Dist: nest-asyncio (>=1.6.0,<2.0.0)
Requires-Dist: openai (>=1.84.0,<2.0.0)
Requires-Dist: pydantic (>=2.11.5,<3.0.0)
Requires-Dist: pydantic-settings (>=2.9.1,<3.0.0)
Requires-Dist: pyyaml (>=6.0.2,<7.0.0)
Requires-Dist: rich (>=14.0.0,<15.0.0)
